README.rst
setup.py
knnimpute/__init__.py
knnimpute/argpartition.py
knnimpute/common.py
knnimpute/few_observed_entries.py
knnimpute/normalized_distance.py
knnimpute/optimistic.py
knnimpute/reference.py
knnimpute.egg-info/PKG-INFO
knnimpute.egg-info/SOURCES.txt
knnimpute.egg-info/dependency_links.txt
knnimpute.egg-info/requires.txt
knnimpute.egg-info/top_level.txt
test/test_distances.py
test/test_knn.py